nlpip/__init__.py
nlpip/prompts/keywords.txt
nlpip/prompts/poem.txt
nlpip/prompts/sentiment.txt
nlpip/prompts/summarize.txt
nlpip-0.1.6.dist-info/LICENSE
nlpip-0.1.6.dist-info/METADATA
nlpip-0.1.6.dist-info/WHEEL
nlpip-0.1.6.dist-info/entry_points.txt
nlpip-0.1.6.dist-info/top_level.txt
nlpip-0.1.6.dist-info/RECORD
