Metadata-Version: 2.1
Name: nlpip
Version: 0.1.6
Summary: A natural language based unix pipeline utility
Author-email: Alan Kang <jania902@gmail.com>
Maintainer-email: Alan Kang <jania902@gmail.com>
License: Copyright (c) 2023 Alan Kang All rights reserved.
Project-URL: Homepage, https://github.com/akngs/nlpip
Project-URL: Bug Reports, https://github.com/akngs/nlpip/issues
Project-URL: Source, https://github.com/akngs/nlpip
Keywords: nlp,llm,chatgpt,openai,unix,pipeline
Classifier: Development Status :: 3 - Alpha
Classifier: Environment :: Console
Classifier: Intended Audience :: Developers
Classifier: Intended Audience :: End Users/Desktop
Classifier: Intended Audience :: Science/Research
Classifier: License :: OSI Approved :: MIT License
Classifier: Programming Language :: Python :: 3
Classifier: Programming Language :: Python :: 3.7
Classifier: Programming Language :: Python :: 3.8
Classifier: Programming Language :: Python :: 3.9
Classifier: Programming Language :: Python :: 3.10
Classifier: Programming Language :: Python :: 3.11
Classifier: Programming Language :: Python :: 3 :: Only
Classifier: Topic :: Text Processing
Classifier: Topic :: Text Processing :: General
Requires-Python: >=3.7
License-File: LICENSE
Requires-Dist: openai
Provides-Extra: dev
Requires-Dist: black ; extra == 'dev'
Requires-Dist: pylint ; extra == 'dev'
